sklearn_export/Export.py
sklearn_export/Template.py
sklearn_export/__init__.py
sklearn_export/package.json
sklearn_export/estimator/__init__.py
sklearn_export/estimator/classifier/Classifier.py
sklearn_export/estimator/classifier/__init__.py
sklearn_export/estimator/classifier/LinearSVC/__init__.py
sklearn_export/estimator/classifier/LogisticRegression/__init__.py
sklearn_export/estimator/classifier/MLPClassifier/__init__.py
sklearn_export/estimator/classifier/NuSVC/__init__.py
sklearn_export/estimator/classifier/SVC/__init__.py
sklearn_export/estimator/regressor/Regressor.py
sklearn_export/estimator/regressor/__init__.py
sklearn_export/estimator/regressor/LinearRegression/__init__.py
sklearn_export/estimator/regressor/LinearSVR/__init__.py
sklearn_export/estimator/regressor/MLPRegressor/__init__.py
sklearn_export/estimator/regressor/SVR/__init__.py
sklearn_export/estimator/scaler/Scaler.py
sklearn_export/estimator/scaler/__init__.py
sklearn_export/estimator/scaler/MinMaxScaler/__init__.py
sklearn_export/estimator/scaler/StandardScaler/__init__.py
sklearn_export-0.0.5.dist-info/METADATA
sklearn_export-0.0.5.dist-info/WHEEL
sklearn_export-0.0.5.dist-info/top_level.txt
sklearn_export-0.0.5.dist-info/RECORD
