Metadata-Version: 2.1
Name: sklearn-export
Version: 0.0.5
Summary: Export sklearn models to Json.
Home-page: https://github.com/gobber/sklearn-export
Author: Charles Gobber
Author-email: charles26f@gmail.com
License: MIT
Keywords: sklearn,scikit-learn
Platform: UNKNOWN
Classifier: Programming Language :: Python :: 2
Classifier: Programming Language :: Python :: 2.7
Classifier: Programming Language :: Python :: 3.4
Classifier: Programming Language :: Python :: 3.5
Classifier: Programming Language :: Python :: 3.6
Classifier: Programming Language :: Python :: 3.7
Requires-Dist: six
Requires-Dist: scikit-learn (>=0.14.1)
